egicli/.travis.yml
egicli/__init__.py
egicli/checkin.py
egicli/cli.py
egicli/endpoint.py
egicli-0.1.1.dist-info/AUTHORS
egicli-0.1.1.dist-info/LICENSE
egicli-0.1.1.dist-info/METADATA
egicli-0.1.1.dist-info/WHEEL
egicli-0.1.1.dist-info/entry_points.txt
egicli-0.1.1.dist-info/pbr.json
egicli-0.1.1.dist-info/top_level.txt
egicli-0.1.1.dist-info/RECORD
