Metadata-Version: 2.1
Name: egicli
Version: 0.1.1
Summary: EGI Command Line Interface
Home-page: UNKNOWN
Author: Enol Fernandez
Author-email: enol.fernandez@egi.eu
License: UNKNOWN
Platform: UNKNOWN
Classifier: Intended Audience :: Information Technology
Classifier: Intended Audience :: Science/Research
Classifier: License :: OSI Approved :: MIT License
Classifier: Operating System :: POSIX :: Linux
Classifier: Programming Language :: Python
Classifier: Programming Language :: Python :: 2
Classifier: Programming Language :: Python :: 2.7
Classifier: Programming Language :: Python :: 3
Classifier: Topic :: System :: Monitoring
Requires-Dist: click
Requires-Dist: tabulate
Requires-Dist: requests
Requires-Dist: six
Requires-Dist: defusedxml
Requires-Dist: pyjwt
